{"title": "fafafa", "id": "tg-481507207301562372", "net.maunium.telegram.pack": {"short_name": "plasticovayazhizn", "hash": "-1741304224"}, "stickers": [{"body": "💀", "url": "mxc://matrix.agreiter.ch/fCBKhKsJbKWQIPmSsPBIvuhF", "info": {"w": 256, "h": 256, "size": 193310, "mimetype": "image/png", "thumbnail_url": "mxc://matrix.agreiter.ch/fCBKhKsJbKWQIPmSsPBIvuhF", "thumbnail_info": {"w": 256, "h": 256, "size": 193310, "mimetype": "image/png"}}, "id": "tg-481507207301562441", "net.maunium.telegram.sticker": {"pack": {"id": "481507207301562372", "short_name": "plasticovayazhizn"}, "id": "481507207301562441", "emoticons": ["💀"]}}, {"body": "💪", "url": "mxc://matrix.agreiter.ch/GXGTWRRcgSHiBMdJHxTXBMas", "info": {"w": 256, "h": 256, "size": 202269, "mimetype": "image/png", "thumbnail_url": "mxc://matrix.agreiter.ch/GXGTWRRcgSHiBMdJHxTXBMas", "thumbnail_info": {"w": 256, "h": 256, "size": 202269, "mimetype": "image/png"}}, "id": "tg-481507207301562447", "net.maunium.telegram.sticker": {"pack": {"id": "481507207301562372", "short_name": "plasticovayazhizn"}, "id": "481507207301562447", "emoticons": ["💪"]}}, {"body": "😔", "url": "mxc://matrix.agreiter.ch/LhNZZgNKcyoCwoTPLjyWIDNo", "info": {"w": 256, "h": 256, "size": 33276, "mimetype": "image/png", "thumbnail_url": "mxc://matrix.agreiter.ch/LhNZZgNKcyoCwoTPLjyWIDNo", "thumbnail_info": {"w": 256, "h": 256, "size": 33276, "mimetype": "image/png"}}, "id": "tg-481507207301564168", "net.maunium.telegram.sticker": {"pack": {"id": "481507207301562372", "short_name": "plasticovayazhizn"}, "id": "481507207301564168", "emoticons": ["😔"]}}, {"body": "😘", "url": "mxc://matrix.agreiter.ch/WOxKFtdlnWsvGRMfuZBoGIMn", "info": {"w": 256, "h": 256, "size": 77869, "mimetype": "image/png", "thumbnail_url": "mxc://matrix.agreiter.ch/WOxKFtdlnWsvGRMfuZBoGIMn", "thumbnail_info": {"w": 256, "h": 256, "size": 77869, "mimetype": "image/png"}}, "id": "tg-481507207301562454", "net.maunium.telegram.sticker": {"pack": {"id": "481507207301562372", "short_name": "plasticovayazhizn"}, "id": "481507207301562454", "emoticons": ["😘"]}}, {"body": "😬", "url": "mxc://matrix.agreiter.ch/FDxjZdeudQJjRxyQycQEYODD", "info": {"w": 256, "h": 256, "size": 74943, "mimetype": "image/png", "thumbnail_url": "mxc://matrix.agreiter.ch/FDxjZdeudQJjRxyQycQEYODD", "thumbnail_info": {"w": 256, "h": 256, "size": 74943, "mimetype": "image/png"}}, "id": "tg-481507207301562456", "net.maunium.telegram.sticker": {"pack": {"id": "481507207301562372", "short_name": "plasticovayazhizn"}, "id": "481507207301562456", "emoticons": ["😬"]}}, {"body": "😔", "url": "mxc://matrix.agreiter.ch/RpbWtnJRppGisBQFrAhYbKqL", "info": {"w": 256, "h": 256, "size": 142368, "mimetype": "image/png", "thumbnail_url": "mxc://matrix.agreiter.ch/RpbWtnJRppGisBQFrAhYbKqL", "thumbnail_info": {"w": 256, "h": 256, "size": 142368, "mimetype": "image/png"}}, "id": "tg-481507207301562460", "net.maunium.telegram.sticker": {"pack": {"id": "481507207301562372", "short_name": "plasticovayazhizn"}, "id": "481507207301562460", "emoticons": ["😔"]}}, {"body": "🐇", "url": "mxc://matrix.agreiter.ch/BLZQWsnnfqkYNqemMsgZCXxt", "info": {"w": 256, "h": 256, "size": 72013, "mimetype": "image/png", "thumbnail_url": "mxc://matrix.agreiter.ch/BLZQWsnnfqkYNqemMsgZCXxt", "thumbnail_info": {"w": 256, "h": 256, "size": 72013, "mimetype": "image/png"}}, "id": "tg-481507207301562464", "net.maunium.telegram.sticker": {"pack": {"id": "481507207301562372", "short_name": "plasticovayazhizn"}, "id": "481507207301562464", "emoticons": ["🐇"]}}, {"body": "😛", "url": "mxc://matrix.agreiter.ch/UToqmbdOPXWyRurypyGvOjtm", "info": {"w": 256, "h": 256, "size": 193416, "mimetype": "image/png", "thumbnail_url": "mxc://matrix.agreiter.ch/UToqmbdOPXWyRurypyGvOjtm", "thumbnail_info": {"w": 256, "h": 256, "size": 193416, "mimetype": "image/png"}}, "id": "tg-481507207301562466", "net.maunium.telegram.sticker": {"pack": {"id": "481507207301562372", "short_name": "plasticovayazhizn"}, "id": "481507207301562466", "emoticons": ["😛"]}}, {"body": "😐", "url": "mxc://matrix.agreiter.ch/vfKzhzVGozMKvsxUbjhQXBeR", "info": {"w": 256, "h": 256, "size": 133715, "mimetype": "image/png", "thumbnail_url": "mxc://matrix.agreiter.ch/vfKzhzVGozMKvsxUbjhQXBeR", "thumbnail_info": {"w": 256, "h": 256, "size": 133715, "mimetype": "image/png"}}, "id": "tg-481507207301562469", "net.maunium.telegram.sticker": {"pack": {"id": "481507207301562372", "short_name": "plasticovayazhizn"}, "id": "481507207301562469", "emoticons": ["😐"]}}, {"body": "😇", "url": "mxc://matrix.agreiter.ch/rbfYNduEDmsIGCxuaMeswVyB", "info": {"w": 256, "h": 256, "size": 53262, "mimetype": "image/png", "thumbnail_url": "mxc://matrix.agreiter.ch/rbfYNduEDmsIGCxuaMeswVyB", "thumbnail_info": {"w": 256, "h": 256, "size": 53262, "mimetype": "image/png"}}, "id": "tg-481507207301563399", "net.maunium.telegram.sticker": {"pack": {"id": "481507207301562372", "short_name": "plasticovayazhizn"}, "id": "481507207301563399", "emoticons": ["😇"]}}, {"body": "🌂", "url": "mxc://matrix.agreiter.ch/XPQagqbDocQPmAlxYrsSaHIn", "info": {"w": 256, "h": 256, "size": 61948, "mimetype": "image/png", "thumbnail_url": "mxc://matrix.agreiter.ch/XPQagqbDocQPmAlxYrsSaHIn", "thumbnail_info": {"w": 256, "h": 256, "size": 61948, "mimetype": "image/png"}}, "id": "tg-481507207301562475", "net.maunium.telegram.sticker": {"pack": {"id": "481507207301562372", "short_name": "plasticovayazhizn"}, "id": "481507207301562475", "emoticons": ["🌂"]}}, {"body": "💤", "url": "mxc://matrix.agreiter.ch/CmFNZhWGgFroeAtgWKmubjgX", "info": {"w": 256, "h": 256, "size": 53805, "mimetype": "image/png", "thumbnail_url": "mxc://matrix.agreiter.ch/CmFNZhWGgFroeAtgWKmubjgX", "thumbnail_info": {"w": 256, "h": 256, "size": 53805, "mimetype": "image/png"}}, "id": "tg-481507207301564175", "net.maunium.telegram.sticker": {"pack": {"id": "481507207301562372", "short_name": "plasticovayazhizn"}, "id": "481507207301564175", "emoticons": ["💤"]}}, {"body": "😧", "url": "mxc://matrix.agreiter.ch/ZafIIJOrEngJOtSCdkbJfUqB", "info": {"w": 256, "h": 256, "size": 95337, "mimetype": "image/png", "thumbnail_url": "mxc://matrix.agreiter.ch/ZafIIJOrEngJOtSCdkbJfUqB", "thumbnail_info": {"w": 256, "h": 256, "size": 95337, "mimetype": "image/png"}}, "id": "tg-481507207301562477", "net.maunium.telegram.sticker": {"pack": {"id": "481507207301562372", "short_name": "plasticovayazhizn"}, "id": "481507207301562477", "emoticons": ["😧"]}}, {"body": "🍉", "url": "mxc://matrix.agreiter.ch/DcAjZmvoRVKktsfvukUSwnEU", "info": {"w": 256, "h": 256, "size": 182292, "mimetype": "image/png", "thumbnail_url": "mxc://matrix.agreiter.ch/DcAjZmvoRVKktsfvukUSwnEU", "thumbnail_info": {"w": 256, "h": 256, "size": 182292, "mimetype": "image/png"}}, "id": "tg-481507207301564174", "net.maunium.telegram.sticker": {"pack": {"id": "481507207301562372", "short_name": "plasticovayazhizn"}, "id": "481507207301564174", "emoticons": ["🍉"]}}, {"body": "🤒", "url": "mxc://matrix.agreiter.ch/ytVoxiUaQQvVcRgnpTypuZRe", "info": {"w": 256, "h": 256, "size": 73689, "mimetype": "image/png", "thumbnail_url": "mxc://matrix.agreiter.ch/ytVoxiUaQQvVcRgnpTypuZRe", "thumbnail_info": {"w": 256, "h": 256, "size": 73689, "mimetype": "image/png"}}, "id": "tg-481507207301562486", "net.maunium.telegram.sticker": {"pack": {"id": "481507207301562372", "short_name": "plasticovayazhizn"}, "id": "481507207301562486", "emoticons": ["🤒"]}}, {"body": "😃", "url": "mxc://matrix.agreiter.ch/SJPeIsWSZdErvGLiCDilyoRj", "info": {"w": 256, "h": 256, "size": 101977, "mimetype": "image/png", "thumbnail_url": "mxc://matrix.agreiter.ch/SJPeIsWSZdErvGLiCDilyoRj", "thumbnail_info": {"w": 256, "h": 256, "size": 101977, "mimetype": "image/png"}}, "id": "tg-481507207301562498", "net.maunium.telegram.sticker": {"pack": {"id": "481507207301562372", "short_name": "plasticovayazhizn"}, "id": "481507207301562498", "emoticons": ["😃"]}}, {"body": "🙉", "url": "mxc://matrix.agreiter.ch/jLNQehwjiIJJCUAMrkzNkLlb", "info": {"w": 256, "h": 256, "size": 108541, "mimetype": "image/png", "thumbnail_url": "mxc://matrix.agreiter.ch/jLNQehwjiIJJCUAMrkzNkLlb", "thumbnail_info": {"w": 256, "h": 256, "size": 108541, "mimetype": "image/png"}}, "id": "tg-481507207301562458", "net.maunium.telegram.sticker": {"pack": {"id": "481507207301562372", "short_name": "plasticovayazhizn"}, "id": "481507207301562458", "emoticons": ["🙉"]}}, {"body": "👠", "url": "mxc://matrix.agreiter.ch/ECaNJjaBnlnVHvyHgjElwOkV", "info": {"w": 256, "h": 256, "size": 242305, "mimetype": "image/png", "thumbnail_url": "mxc://matrix.agreiter.ch/ECaNJjaBnlnVHvyHgjElwOkV", "thumbnail_info": {"w": 256, "h": 256, "size": 242305, "mimetype": "image/png"}}, "id": "tg-481507207301562562", "net.maunium.telegram.sticker": {"pack": {"id": "481507207301562372", "short_name": "plasticovayazhizn"}, "id": "481507207301562562", "emoticons": ["👠"]}}, {"body": "😔", "url": "mxc://matrix.agreiter.ch/tsYhjJOFXbfSicLrRiGFTKyp", "info": {"w": 256, "h": 256, "size": 51856, "mimetype": "image/png", "thumbnail_url": "mxc://matrix.agreiter.ch/tsYhjJOFXbfSicLrRiGFTKyp", "thumbnail_info": {"w": 256, "h": 256, "size": 51856, "mimetype": "image/png"}}, "id": "tg-481507207301564184", "net.maunium.telegram.sticker": {"pack": {"id": "481507207301562372", "short_name": "plasticovayazhizn"}, "id": "481507207301564184", "emoticons": ["😔"]}}, {"body": "😳", "url": "mxc://matrix.agreiter.ch/enMOVBvESkBcSPOuDuQVqVGN", "info": {"w": 256, "h": 256, "size": 58400, "mimetype": "image/png", "thumbnail_url": "mxc://matrix.agreiter.ch/enMOVBvESkBcSPOuDuQVqVGN", "thumbnail_info": {"w": 256, "h": 256, "size": 58400, "mimetype": "image/png"}}, "id": "tg-481507207301562586", "net.maunium.telegram.sticker": {"pack": {"id": "481507207301562372", "short_name": "plasticovayazhizn"}, "id": "481507207301562586", "emoticons": ["😳"]}}, {"body": "😺", "url": "mxc://matrix.agreiter.ch/WVTHegkaRMHWLsNKVwWdAOzE", "info": {"w": 256, "h": 256, "size": 147331, "mimetype": "image/png", "thumbnail_url": "mxc://matrix.agreiter.ch/WVTHegkaRMHWLsNKVwWdAOzE", "thumbnail_info": {"w": 256, "h": 256, "size": 147331, "mimetype": "image/png"}}, "id": "tg-481507207301562589", "net.maunium.telegram.sticker": {"pack": {"id": "481507207301562372", "short_name": "plasticovayazhizn"}, "id": "481507207301562589", "emoticons": ["😺"]}}, {"body": "🙄", "url": "mxc://matrix.agreiter.ch/tbbuDBKcuqwcDamhtGgDDjQu", "info": {"w": 256, "h": 256, "size": 151510, "mimetype": "image/png", "thumbnail_url": "mxc://matrix.agreiter.ch/tbbuDBKcuqwcDamhtGgDDjQu", "thumbnail_info": {"w": 256, "h": 256, "size": 151510, "mimetype": "image/png"}}, "id": "tg-481507207301562628", "net.maunium.telegram.sticker": {"pack": {"id": "481507207301562372", "short_name": "plasticovayazhizn"}, "id": "481507207301562628", "emoticons": ["🙄"]}}, {"body": "🕶", "url": "mxc://matrix.agreiter.ch/ncziGvcLWJmEuJhMYIVMcvEG", "info": {"w": 256, "h": 256, "size": 68303, "mimetype": "image/png", "thumbnail_url": "mxc://matrix.agreiter.ch/ncziGvcLWJmEuJhMYIVMcvEG", "thumbnail_info": {"w": 256, "h": 256, "size": 68303, "mimetype": "image/png"}}, "id": "tg-481507207301562630", "net.maunium.telegram.sticker": {"pack": {"id": "481507207301562372", "short_name": "plasticovayazhizn"}, "id": "481507207301562630", "emoticons": ["🕶"]}}, {"body": "😓", "url": "mxc://matrix.agreiter.ch/mEACVqVBXSwOsFyHadBtAMBS", "info": {"w": 256, "h": 256, "size": 50458, "mimetype": "image/png", "thumbnail_url": "mxc://matrix.agreiter.ch/mEACVqVBXSwOsFyHadBtAMBS", "thumbnail_info": {"w": 256, "h": 256, "size": 50458, "mimetype": "image/png"}}, "id": "tg-481507207301562632", "net.maunium.telegram.sticker": {"pack": {"id": "481507207301562372", "short_name": "plasticovayazhizn"}, "id": "481507207301562632", "emoticons": ["😓"]}}, {"body": "🐺", "url": "mxc://matrix.agreiter.ch/xuulxggWtQquSNKndZhMoTol", "info": {"w": 256, "h": 256, "size": 88123, "mimetype": "image/png", "thumbnail_url": "mxc://matrix.agreiter.ch/xuulxggWtQquSNKndZhMoTol", "thumbnail_info": {"w": 256, "h": 256, "size": 88123, "mimetype": "image/png"}}, "id": "tg-481507207301563357", "net.maunium.telegram.sticker": {"pack": {"id": "481507207301562372", "short_name": "plasticovayazhizn"}, "id": "481507207301563357", "emoticons": ["🐺"]}}, {"body": "😔", "url": "mxc://matrix.agreiter.ch/YIRwIHixkUfHiniKKqngFLKs", "info": {"w": 256, "h": 256, "size": 23772, "mimetype": "image/png", "thumbnail_url": "mxc://matrix.agreiter.ch/YIRwIHixkUfHiniKKqngFLKs", "thumbnail_info": {"w": 256, "h": 256, "size": 23772, "mimetype": "image/png"}}, "id": "tg-481507207301564194", "net.maunium.telegram.sticker": {"pack": {"id": "481507207301562372", "short_name": "plasticovayazhizn"}, "id": "481507207301564194", "emoticons": ["😔"]}}, {"body": "🤔", "url": "mxc://matrix.agreiter.ch/HNlWEVQwYJvrVAueQtvGuheB", "info": {"w": 256, "h": 256, "size": 196309, "mimetype": "image/png", "thumbnail_url": "mxc://matrix.agreiter.ch/HNlWEVQwYJvrVAueQtvGuheB", "thumbnail_info": {"w": 256, "h": 256, "size": 196309, "mimetype": "image/png"}}, "id": "tg-481507207301563359", "net.maunium.telegram.sticker": {"pack": {"id": "481507207301562372", "short_name": "plasticovayazhizn"}, "id": "481507207301563359", "emoticons": ["🤔"]}}, {"body": "😁", "url": "mxc://matrix.agreiter.ch/eqCmayzSjbRyTgzlfJdWYZMa", "info": {"w": 256, "h": 256, "size": 69274, "mimetype": "image/png", "thumbnail_url": "mxc://matrix.agreiter.ch/eqCmayzSjbRyTgzlfJdWYZMa", "thumbnail_info": {"w": 256, "h": 256, "size": 69274, "mimetype": "image/png"}}, "id": "tg-481507207301563361", "net.maunium.telegram.sticker": {"pack": {"id": "481507207301562372", "short_name": "plasticovayazhizn"}, "id": "481507207301563361", "emoticons": ["😁"]}}, {"body": "😓", "url": "mxc://matrix.agreiter.ch/FODBIDkMIyTqEKVxRIGQibPC", "info": {"w": 256, "h": 256, "size": 40191, "mimetype": "image/png", "thumbnail_url": "mxc://matrix.agreiter.ch/FODBIDkMIyTqEKVxRIGQibPC", "thumbnail_info": {"w": 256, "h": 256, "size": 40191, "mimetype": "image/png"}}, "id": "tg-481507207301564176", "net.maunium.telegram.sticker": {"pack": {"id": "481507207301562372", "short_name": "plasticovayazhizn"}, "id": "481507207301564176", "emoticons": ["😓"]}}, {"body": "😁", "url": "mxc://matrix.agreiter.ch/BczugTOZHskysvFHOWYLRVdf", "info": {"w": 256, "h": 256, "size": 210212, "mimetype": "image/png", "thumbnail_url": "mxc://matrix.agreiter.ch/BczugTOZHskysvFHOWYLRVdf", "thumbnail_info": {"w": 256, "h": 256, "size": 210212, "mimetype": "image/png"}}, "id": "tg-481507207301563374", "net.maunium.telegram.sticker": {"pack": {"id": "481507207301562372", "short_name": "plasticovayazhizn"}, "id": "481507207301563374", "emoticons": ["😁"]}}, {"body": "🍷", "url": "mxc://matrix.agreiter.ch/faZvWxQIouScRtuXxsJVhOML", "info": {"w": 256, "h": 256, "size": 117717, "mimetype": "image/png", "thumbnail_url": "mxc://matrix.agreiter.ch/faZvWxQIouScRtuXxsJVhOML", "thumbnail_info": {"w": 256, "h": 256, "size": 117717, "mimetype": "image/png"}}, "id": "tg-481507207301563383", "net.maunium.telegram.sticker": {"pack": {"id": "481507207301562372", "short_name": "plasticovayazhizn"}, "id": "481507207301563383", "emoticons": ["🍷"]}}, {"body": "😎", "url": "mxc://matrix.agreiter.ch/tUXfaSXqQVDaQdwCjiWDmLGK", "info": {"w": 256, "h": 256, "size": 191117, "mimetype": "image/png", "thumbnail_url": "mxc://matrix.agreiter.ch/tUXfaSXqQVDaQdwCjiWDmLGK", "thumbnail_info": {"w": 256, "h": 256, "size": 191117, "mimetype": "image/png"}}, "id": "tg-481507207301563389", "net.maunium.telegram.sticker": {"pack": {"id": "481507207301562372", "short_name": "plasticovayazhizn"}, "id": "481507207301563389", "emoticons": ["😎"]}}, {"body": "🙃", "url": "mxc://matrix.agreiter.ch/eCCulfQLsCDdiKJZrOpAPAUE", "info": {"w": 256, "h": 256, "size": 152614, "mimetype": "image/png", "thumbnail_url": "mxc://matrix.agreiter.ch/eCCulfQLsCDdiKJZrOpAPAUE", "thumbnail_info": {"w": 256, "h": 256, "size": 152614, "mimetype": "image/png"}}, "id": "tg-481507207301563395", "net.maunium.telegram.sticker": {"pack": {"id": "481507207301562372", "short_name": "plasticovayazhizn"}, "id": "481507207301563395", "emoticons": ["🙃"]}}, {"body": "💋", "url": "mxc://matrix.agreiter.ch/zXsKUFnnASKTdqNLguJeaZdC", "info": {"w": 256, "h": 256, "size": 58897, "mimetype": "image/png", "thumbnail_url": "mxc://matrix.agreiter.ch/zXsKUFnnASKTdqNLguJeaZdC", "thumbnail_info": {"w": 256, "h": 256, "size": 58897, "mimetype": "image/png"}}, "id": "tg-481507207301563397", "net.maunium.telegram.sticker": {"pack": {"id": "481507207301562372", "short_name": "plasticovayazhizn"}, "id": "481507207301563397", "emoticons": ["💋"]}}, {"body": "❄", "url": "mxc://matrix.agreiter.ch/oEZZkorMXrtYdUsPWPkTRRym", "info": {"w": 256, "h": 256, "size": 93470, "mimetype": "image/png", "thumbnail_url": "mxc://matrix.agreiter.ch/oEZZkorMXrtYdUsPWPkTRRym", "thumbnail_info": {"w": 256, "h": 256, "size": 93470, "mimetype": "image/png"}}, "id": "tg-481507207301563799", "net.maunium.telegram.sticker": {"pack": {"id": "481507207301562372", "short_name": "plasticovayazhizn"}, "id": "481507207301563799", "emoticons": ["❄"]}}, {"body": "😔", "url": "mxc://matrix.agreiter.ch/cpNrIemtIHobkAXFuszhvSUA", "info": {"w": 256, "h": 256, "size": 32349, "mimetype": "image/png", "thumbnail_url": "mxc://matrix.agreiter.ch/cpNrIemtIHobkAXFuszhvSUA", "thumbnail_info": {"w": 256, "h": 256, "size": 32349, "mimetype": "image/png"}}, "id": "tg-481507207301563403", "net.maunium.telegram.sticker": {"pack": {"id": "481507207301562372", "short_name": "plasticovayazhizn"}, "id": "481507207301563403", "emoticons": ["😔"]}}, {"body": "❤", "url": "mxc://matrix.agreiter.ch/mgUqHFtSvSyvwaTijVQIZUdv", "info": {"w": 256, "h": 256, "size": 150885, "mimetype": "image/png", "thumbnail_url": "mxc://matrix.agreiter.ch/mgUqHFtSvSyvwaTijVQIZUdv", "thumbnail_info": {"w": 256, "h": 256, "size": 150885, "mimetype": "image/png"}}, "id": "tg-481507207301563473", "net.maunium.telegram.sticker": {"pack": {"id": "481507207301562372", "short_name": "plasticovayazhizn"}, "id": "481507207301563473", "emoticons": ["❤"]}}, {"body": "🙄", "url": "mxc://matrix.agreiter.ch/OtBTbTWAQkuiRmVfBYJvCTch", "info": {"w": 256, "h": 256, "size": 306387, "mimetype": "image/png", "thumbnail_url": "mxc://matrix.agreiter.ch/OtBTbTWAQkuiRmVfBYJvCTch", "thumbnail_info": {"w": 256, "h": 256, "size": 306387, "mimetype": "image/png"}}, "id": "tg-481507207301563475", "net.maunium.telegram.sticker": {"pack": {"id": "481507207301562372", "short_name": "plasticovayazhizn"}, "id": "481507207301563475", "emoticons": ["🙄"]}}, {"body": "🙈", "url": "mxc://matrix.agreiter.ch/kbFKwJeZrPnabJiyBbnrnnoL", "info": {"w": 256, "h": 256, "size": 152560, "mimetype": "image/png", "thumbnail_url": "mxc://matrix.agreiter.ch/kbFKwJeZrPnabJiyBbnrnnoL", "thumbnail_info": {"w": 256, "h": 256, "size": 152560, "mimetype": "image/png"}}, "id": "tg-481507207301563801", "net.maunium.telegram.sticker": {"pack": {"id": "481507207301562372", "short_name": "plasticovayazhizn"}, "id": "481507207301563801", "emoticons": ["🙈"]}}, {"body": "💤", "url": "mxc://matrix.agreiter.ch/zzCHqPgRSFYFUgWvJJDpmojA", "info": {"w": 256, "h": 256, "size": 94813, "mimetype": "image/png", "thumbnail_url": "mxc://matrix.agreiter.ch/zzCHqPgRSFYFUgWvJJDpmojA", "thumbnail_info": {"w": 256, "h": 256, "size": 94813, "mimetype": "image/png"}}, "id": "tg-481507207301563803", "net.maunium.telegram.sticker": {"pack": {"id": "481507207301562372", "short_name": "plasticovayazhizn"}, "id": "481507207301563803", "emoticons": ["💤"]}}, {"body": "😶", "url": "mxc://matrix.agreiter.ch/yXEMxbMSthCWILKJvTAFyzGe", "info": {"w": 256, "h": 256, "size": 80963, "mimetype": "image/png", "thumbnail_url": "mxc://matrix.agreiter.ch/yXEMxbMSthCWILKJvTAFyzGe", "thumbnail_info": {"w": 256, "h": 256, "size": 80963, "mimetype": "image/png"}}, "id": "tg-481507207301564146", "net.maunium.telegram.sticker": {"pack": {"id": "481507207301562372", "short_name": "plasticovayazhizn"}, "id": "481507207301564146", "emoticons": ["😶"]}}, {"body": "🐕", "url": "mxc://matrix.agreiter.ch/coNKGiPYFDbTphKaoygyUBKC", "info": {"w": 256, "h": 256, "size": 87991, "mimetype": "image/png", "thumbnail_url": "mxc://matrix.agreiter.ch/coNKGiPYFDbTphKaoygyUBKC", "thumbnail_info": {"w": 256, "h": 256, "size": 87991, "mimetype": "image/png"}}, "id": "tg-481507207301564149", "net.maunium.telegram.sticker": {"pack": {"id": "481507207301562372", "short_name": "plasticovayazhizn"}, "id": "481507207301564149", "emoticons": ["🐕"]}}, {"body": "🤔", "url": "mxc://matrix.agreiter.ch/uwDPeVJeWZkhykymeLSODNvl", "info": {"w": 256, "h": 256, "size": 90678, "mimetype": "image/png", "thumbnail_url": "mxc://matrix.agreiter.ch/uwDPeVJeWZkhykymeLSODNvl", "thumbnail_info": {"w": 256, "h": 256, "size": 90678, "mimetype": "image/png"}}, "id": "tg-481507207301564193", "net.maunium.telegram.sticker": {"pack": {"id": "481507207301562372", "short_name": "plasticovayazhizn"}, "id": "481507207301564193", "emoticons": ["🤔"]}}, {"body": "😢", "url": "mxc://matrix.agreiter.ch/dXvgJYRJZWWTjBfSNuWRBDeM", "info": {"w": 256, "h": 256, "size": 100093, "mimetype": "image/png", "thumbnail_url": "mxc://matrix.agreiter.ch/dXvgJYRJZWWTjBfSNuWRBDeM", "thumbnail_info": {"w": 256, "h": 256, "size": 100093, "mimetype": "image/png"}}, "id": "tg-481507207301564151", "net.maunium.telegram.sticker": {"pack": {"id": "481507207301562372", "short_name": "plasticovayazhizn"}, "id": "481507207301564151", "emoticons": ["😢"]}}, {"body": "🙈", "url": "mxc://matrix.agreiter.ch/dkupgTuxQOdcgaOezEmDuhPQ", "info": {"w": 256, "h": 256, "size": 136664, "mimetype": "image/png", "thumbnail_url": "mxc://matrix.agreiter.ch/dkupgTuxQOdcgaOezEmDuhPQ", "thumbnail_info": {"w": 256, "h": 256, "size": 136664, "mimetype": "image/png"}}, "id": "tg-481507207301563401", "net.maunium.telegram.sticker": {"pack": {"id": "481507207301562372", "short_name": "plasticovayazhizn"}, "id": "481507207301563401", "emoticons": ["🙈"]}}, {"body": "😺", "url": "mxc://matrix.agreiter.ch/eigNWgMGkaIGyreXElbnbFBm", "info": {"w": 256, "h": 256, "size": 76737, "mimetype": "image/png", "thumbnail_url": "mxc://matrix.agreiter.ch/eigNWgMGkaIGyreXElbnbFBm", "thumbnail_info": {"w": 256, "h": 256, "size": 76737, "mimetype": "image/png"}}, "id": "tg-481507207301562462", "net.maunium.telegram.sticker": {"pack": {"id": "481507207301562372", "short_name": "plasticovayazhizn"}, "id": "481507207301562462", "emoticons": ["😺"]}}, {"body": "😺", "url": "mxc://matrix.agreiter.ch/OINosMHMXAXbVImLtusRAiNc", "info": {"w": 256, "h": 256, "size": 131397, "mimetype": "image/png", "thumbnail_url": "mxc://matrix.agreiter.ch/OINosMHMXAXbVImLtusRAiNc", "thumbnail_info": {"w": 256, "h": 256, "size": 131397, "mimetype": "image/png"}}, "id": "tg-481507207301564152", "net.maunium.telegram.sticker": {"pack": {"id": "481507207301562372", "short_name": "plasticovayazhizn"}, "id": "481507207301564152", "emoticons": ["😺"]}}, {"body": "🤔", "url": "mxc://matrix.agreiter.ch/SClUANsnntduwMZyuImYaYPw", "info": {"w": 256, "h": 256, "size": 19405, "mimetype": "image/png", "thumbnail_url": "mxc://matrix.agreiter.ch/SClUANsnntduwMZyuImYaYPw", "thumbnail_info": {"w": 256, "h": 256, "size": 19405, "mimetype": "image/png"}}, "id": "tg-481507207301564164", "net.maunium.telegram.sticker": {"pack": {"id": "481507207301562372", "short_name": "plasticovayazhizn"}, "id": "481507207301564164", "emoticons": ["🤔"]}}, {"body": "🌧", "url": "mxc://matrix.agreiter.ch/xWxngwNYDQfQOGUXTWJRYMOR", "info": {"w": 256, "h": 256, "size": 46210, "mimetype": "image/png", "thumbnail_url": "mxc://matrix.agreiter.ch/xWxngwNYDQfQOGUXTWJRYMOR", "thumbnail_info": {"w": 256, "h": 256, "size": 46210, "mimetype": "image/png"}}, "id": "tg-481507207301564165", "net.maunium.telegram.sticker": {"pack": {"id": "481507207301562372", "short_name": "plasticovayazhizn"}, "id": "481507207301564165", "emoticons": ["🌧"]}}, {"body": "😒", "url": "mxc://matrix.agreiter.ch/KoyOxVOWajnigPsDJPydaLOk", "info": {"w": 256, "h": 256, "size": 53431, "mimetype": "image/png", "thumbnail_url": "mxc://matrix.agreiter.ch/KoyOxVOWajnigPsDJPydaLOk", "thumbnail_info": {"w": 256, "h": 256, "size": 53431, "mimetype": "image/png"}}, "id": "tg-481507207301564166", "net.maunium.telegram.sticker": {"pack": {"id": "481507207301562372", "short_name": "plasticovayazhizn"}, "id": "481507207301564166", "emoticons": ["😒"]}}, {"body": "😄", "url": "mxc://matrix.agreiter.ch/mvGwbnUYeSbUerYXPLXspklZ", "info": {"w": 256, "h": 256, "size": 29438, "mimetype": "image/png", "thumbnail_url": "mxc://matrix.agreiter.ch/mvGwbnUYeSbUerYXPLXspklZ", "thumbnail_info": {"w": 256, "h": 256, "size": 29438, "mimetype": "image/png"}}, "id": "tg-481507207301564167", "net.maunium.telegram.sticker": {"pack": {"id": "481507207301562372", "short_name": "plasticovayazhizn"}, "id": "481507207301564167", "emoticons": ["😄"]}}, {"body": "☕", "url": "mxc://matrix.agreiter.ch/fGnmCtobvtuoAoImzYuNCZQd", "info": {"w": 256, "h": 256, "size": 71794, "mimetype": "image/png", "thumbnail_url": "mxc://matrix.agreiter.ch/fGnmCtobvtuoAoImzYuNCZQd", "thumbnail_info": {"w": 256, "h": 256, "size": 71794, "mimetype": "image/png"}}, "id": "tg-481507207301564169", "net.maunium.telegram.sticker": {"pack": {"id": "481507207301562372", "short_name": "plasticovayazhizn"}, "id": "481507207301564169", "emoticons": ["☕"]}}, {"body": "😨", "url": "mxc://matrix.agreiter.ch/hxDpFgNUkLybmHzOWUFoDnjz", "info": {"w": 256, "h": 256, "size": 175617, "mimetype": "image/png", "thumbnail_url": "mxc://matrix.agreiter.ch/hxDpFgNUkLybmHzOWUFoDnjz", "thumbnail_info": {"w": 256, "h": 256, "size": 175617, "mimetype": "image/png"}}, "id": "tg-481507207301562488", "net.maunium.telegram.sticker": {"pack": {"id": "481507207301562372", "short_name": "plasticovayazhizn"}, "id": "481507207301562488", "emoticons": ["😨"]}}, {"body": "🍷", "url": "mxc://matrix.agreiter.ch/ZUslzSAkwkatBuhNdqClbUqq", "info": {"w": 256, "h": 256, "size": 175490, "mimetype": "image/png", "thumbnail_url": "mxc://matrix.agreiter.ch/ZUslzSAkwkatBuhNdqClbUqq", "thumbnail_info": {"w": 256, "h": 256, "size": 175490, "mimetype": "image/png"}}, "id": "tg-481507207301564170", "net.maunium.telegram.sticker": {"pack": {"id": "481507207301562372", "short_name": "plasticovayazhizn"}, "id": "481507207301564170", "emoticons": ["🍷"]}}, {"body": "❤", "url": "mxc://matrix.agreiter.ch/XXpZMogXNSVTgPMmTpEXtZOc", "info": {"w": 256, "h": 256, "size": 78056, "mimetype": "image/png", "thumbnail_url": "mxc://matrix.agreiter.ch/XXpZMogXNSVTgPMmTpEXtZOc", "thumbnail_info": {"w": 256, "h": 256, "size": 78056, "mimetype": "image/png"}}, "id": "tg-481507207301564172", "net.maunium.telegram.sticker": {"pack": {"id": "481507207301562372", "short_name": "plasticovayazhizn"}, "id": "481507207301564172", "emoticons": ["❤"]}}, {"body": "😎", "url": "mxc://matrix.agreiter.ch/vrfBLRceYjAdzLgbQYioInRN", "info": {"w": 256, "h": 256, "size": 44841, "mimetype": "image/png", "thumbnail_url": "mxc://matrix.agreiter.ch/vrfBLRceYjAdzLgbQYioInRN", "thumbnail_info": {"w": 256, "h": 256, "size": 44841, "mimetype": "image/png"}}, "id": "tg-481507207301564177", "net.maunium.telegram.sticker": {"pack": {"id": "481507207301562372", "short_name": "plasticovayazhizn"}, "id": "481507207301564177", "emoticons": ["😎"]}}, {"body": "❤", "url": "mxc://matrix.agreiter.ch/fbaDFlfnqnZZeXsqZJPHvGso", "info": {"w": 256, "h": 256, "size": 85054, "mimetype": "image/png", "thumbnail_url": "mxc://matrix.agreiter.ch/fbaDFlfnqnZZeXsqZJPHvGso", "thumbnail_info": {"w": 256, "h": 256, "size": 85054, "mimetype": "image/png"}}, "id": "tg-481507207301564178", "net.maunium.telegram.sticker": {"pack": {"id": "481507207301562372", "short_name": "plasticovayazhizn"}, "id": "481507207301564178", "emoticons": ["❤"]}}, {"body": "🌞", "url": "mxc://matrix.agreiter.ch/xNWTIYTbnNBuLhLyOoASUCYK", "info": {"w": 256, "h": 256, "size": 75731, "mimetype": "image/png", "thumbnail_url": "mxc://matrix.agreiter.ch/xNWTIYTbnNBuLhLyOoASUCYK", "thumbnail_info": {"w": 256, "h": 256, "size": 75731, "mimetype": "image/png"}}, "id": "tg-481507207301564179", "net.maunium.telegram.sticker": {"pack": {"id": "481507207301562372", "short_name": "plasticovayazhizn"}, "id": "481507207301564179", "emoticons": ["🌞"]}}, {"body": "🙃", "url": "mxc://matrix.agreiter.ch/ByEUpLkKuQDVoRlzWnEEuMfs", "info": {"w": 256, "h": 256, "size": 115636, "mimetype": "image/png", "thumbnail_url": "mxc://matrix.agreiter.ch/ByEUpLkKuQDVoRlzWnEEuMfs", "thumbnail_info": {"w": 256, "h": 256, "size": 115636, "mimetype": "image/png"}}, "id": "tg-481507207301564182", "net.maunium.telegram.sticker": {"pack": {"id": "481507207301562372", "short_name": "plasticovayazhizn"}, "id": "481507207301564182", "emoticons": ["🙃"]}}, {"body": "❤", "url": "mxc://matrix.agreiter.ch/gjoEKTvaTGoaUsXUGKlqDnKC", "info": {"w": 256, "h": 256, "size": 186841, "mimetype": "image/png", "thumbnail_url": "mxc://matrix.agreiter.ch/gjoEKTvaTGoaUsXUGKlqDnKC", "thumbnail_info": {"w": 256, "h": 256, "size": 186841, "mimetype": "image/png"}}, "id": "tg-481507207301564183", "net.maunium.telegram.sticker": {"pack": {"id": "481507207301562372", "short_name": "plasticovayazhizn"}, "id": "481507207301564183", "emoticons": ["❤"]}}, {"body": "🦊", "url": "mxc://matrix.agreiter.ch/jbPCglQRjapZfHJdQUBFBabE", "info": {"w": 256, "h": 256, "size": 151412, "mimetype": "image/png", "thumbnail_url": "mxc://matrix.agreiter.ch/jbPCglQRjapZfHJdQUBFBabE", "thumbnail_info": {"w": 256, "h": 256, "size": 151412, "mimetype": "image/png"}}, "id": "tg-481507207301564186", "net.maunium.telegram.sticker": {"pack": {"id": "481507207301562372", "short_name": "plasticovayazhizn"}, "id": "481507207301564186", "emoticons": ["🦊"]}}, {"body": "☂", "url": "mxc://matrix.agreiter.ch/dauxHPDtlZJJWEsUpJiBDtIj", "info": {"w": 256, "h": 256, "size": 108000, "mimetype": "image/png", "thumbnail_url": "mxc://matrix.agreiter.ch/dauxHPDtlZJJWEsUpJiBDtIj", "thumbnail_info": {"w": 256, "h": 256, "size": 108000, "mimetype": "image/png"}}, "id": "tg-481507207301564187", "net.maunium.telegram.sticker": {"pack": {"id": "481507207301562372", "short_name": "plasticovayazhizn"}, "id": "481507207301564187", "emoticons": ["☂"]}}, {"body": "☹", "url": "mxc://matrix.agreiter.ch/FzQxtqqxkiDKxKGGmfCWVMYC", "info": {"w": 256, "h": 256, "size": 52368, "mimetype": "image/png", "thumbnail_url": "mxc://matrix.agreiter.ch/FzQxtqqxkiDKxKGGmfCWVMYC", "thumbnail_info": {"w": 256, "h": 256, "size": 52368, "mimetype": "image/png"}}, "id": "tg-481507207301564188", "net.maunium.telegram.sticker": {"pack": {"id": "481507207301562372", "short_name": "plasticovayazhizn"}, "id": "481507207301564188", "emoticons": ["☹"]}}, {"body": "😓", "url": "mxc://matrix.agreiter.ch/CIPnOoILXoeLuKkdZXlpiGwO", "info": {"w": 256, "h": 256, "size": 164229, "mimetype": "image/png", "thumbnail_url": "mxc://matrix.agreiter.ch/CIPnOoILXoeLuKkdZXlpiGwO", "thumbnail_info": {"w": 256, "h": 256, "size": 164229, "mimetype": "image/png"}}, "id": "tg-481507207301564192", "net.maunium.telegram.sticker": {"pack": {"id": "481507207301562372", "short_name": "plasticovayazhizn"}, "id": "481507207301564192", "emoticons": ["😓"]}}, {"body": "❤", "url": "mxc://matrix.agreiter.ch/GWhDlVyvOUBXQDRgbyhajrlP", "info": {"w": 256, "h": 256, "size": 29615, "mimetype": "image/png", "thumbnail_url": "mxc://matrix.agreiter.ch/GWhDlVyvOUBXQDRgbyhajrlP", "thumbnail_info": {"w": 256, "h": 256, "size": 29615, "mimetype": "image/png"}}, "id": "tg-481507207301564191", "net.maunium.telegram.sticker": {"pack": {"id": "481507207301562372", "short_name": "plasticovayazhizn"}, "id": "481507207301564191", "emoticons": ["❤"]}}, {"body": "😎", "url": "mxc://matrix.agreiter.ch/SfGzMZdvPQIEBaMHfjSiSChX", "info": {"w": 256, "h": 256, "size": 135155, "mimetype": "image/png", "thumbnail_url": "mxc://matrix.agreiter.ch/SfGzMZdvPQIEBaMHfjSiSChX", "thumbnail_info": {"w": 256, "h": 256, "size": 135155, "mimetype": "image/png"}}, "id": "tg-481507207301564195", "net.maunium.telegram.sticker": {"pack": {"id": "481507207301562372", "short_name": "plasticovayazhizn"}, "id": "481507207301564195", "emoticons": ["😎"]}}, {"body": "😘", "url": "mxc://matrix.agreiter.ch/MWmMCKnXJMVdyTATNjbmjgRp", "info": {"w": 256, "h": 256, "size": 126107, "mimetype": "image/png", "thumbnail_url": "mxc://matrix.agreiter.ch/MWmMCKnXJMVdyTATNjbmjgRp", "thumbnail_info": {"w": 256, "h": 256, "size": 126107, "mimetype": "image/png"}}, "id": "tg-481507207301564196", "net.maunium.telegram.sticker": {"pack": {"id": "481507207301562372", "short_name": "plasticovayazhizn"}, "id": "481507207301564196", "emoticons": ["😘"]}}, {"body": "😣", "url": "mxc://matrix.agreiter.ch/KQXMbNpPDUkVpTWVeSLtlOcd", "info": {"w": 256, "h": 256, "size": 60185, "mimetype": "image/png", "thumbnail_url": "mxc://matrix.agreiter.ch/KQXMbNpPDUkVpTWVeSLtlOcd", "thumbnail_info": {"w": 256, "h": 256, "size": 60185, "mimetype": "image/png"}}, "id": "tg-481507207301564197", "net.maunium.telegram.sticker": {"pack": {"id": "481507207301562372", "short_name": "plasticovayazhizn"}, "id": "481507207301564197", "emoticons": ["😣"]}}, {"body": "😎", "url": "mxc://matrix.agreiter.ch/kEAPIQUdoMLPDsbgSjCfFzZB", "info": {"w": 256, "h": 256, "size": 35020, "mimetype": "image/png", "thumbnail_url": "mxc://matrix.agreiter.ch/kEAPIQUdoMLPDsbgSjCfFzZB", "thumbnail_info": {"w": 256, "h": 256, "size": 35020, "mimetype": "image/png"}}, "id": "tg-481507207301564198", "net.maunium.telegram.sticker": {"pack": {"id": "481507207301562372", "short_name": "plasticovayazhizn"}, "id": "481507207301564198", "emoticons": ["😎"]}}, {"body": "😬", "url": "mxc://matrix.agreiter.ch/YaJMPnyQHycEpyVTCJNrKCKP", "info": {"w": 256, "h": 256, "size": 189349, "mimetype": "image/png", "thumbnail_url": "mxc://matrix.agreiter.ch/YaJMPnyQHycEpyVTCJNrKCKP", "thumbnail_info": {"w": 256, "h": 256, "size": 189349, "mimetype": "image/png"}}, "id": "tg-481507207301564199", "net.maunium.telegram.sticker": {"pack": {"id": "481507207301562372", "short_name": "plasticovayazhizn"}, "id": "481507207301564199", "emoticons": ["😬"]}}, {"body": "😐", "url": "mxc://matrix.agreiter.ch/nYlxwzOCTfUdOlYuUgWETXzB", "info": {"w": 256, "h": 256, "size": 76541, "mimetype": "image/png", "thumbnail_url": "mxc://matrix.agreiter.ch/nYlxwzOCTfUdOlYuUgWETXzB", "thumbnail_info": {"w": 256, "h": 256, "size": 76541, "mimetype": "image/png"}}, "id": "tg-481507207301564200", "net.maunium.telegram.sticker": {"pack": {"id": "481507207301562372", "short_name": "plasticovayazhizn"}, "id": "481507207301564200", "emoticons": ["😐"]}}, {"body": "💤", "url": "mxc://matrix.agreiter.ch/maNqiLqipxLJVzQTNFTggOaJ", "info": {"w": 256, "h": 256, "size": 119607, "mimetype": "image/png", "thumbnail_url": "mxc://matrix.agreiter.ch/maNqiLqipxLJVzQTNFTggOaJ", "thumbnail_info": {"w": 256, "h": 256, "size": 119607, "mimetype": "image/png"}}, "id": "tg-481507207301564217", "net.maunium.telegram.sticker": {"pack": {"id": "481507207301562372", "short_name": "plasticovayazhizn"}, "id": "481507207301564217", "emoticons": ["💤"]}}, {"body": "❤", "url": "mxc://matrix.agreiter.ch/gaxQIrXWYNDAVrGYVUqLPkqg", "info": {"w": 256, "h": 256, "size": 108985, "mimetype": "image/png", "thumbnail_url": "mxc://matrix.agreiter.ch/gaxQIrXWYNDAVrGYVUqLPkqg", "thumbnail_info": {"w": 256, "h": 256, "size": 108985, "mimetype": "image/png"}}, "id": "tg-481507207301564218", "net.maunium.telegram.sticker": {"pack": {"id": "481507207301562372", "short_name": "plasticovayazhizn"}, "id": "481507207301564218", "emoticons": ["❤"]}}, {"body": "😕", "url": "mxc://matrix.agreiter.ch/RCZLJTTmUikRsMajCiVwczrQ", "info": {"w": 256, "h": 256, "size": 142019, "mimetype": "image/png", "thumbnail_url": "mxc://matrix.agreiter.ch/RCZLJTTmUikRsMajCiVwczrQ", "thumbnail_info": {"w": 256, "h": 256, "size": 142019, "mimetype": "image/png"}}, "id": "tg-481507207301564224", "net.maunium.telegram.sticker": {"pack": {"id": "481507207301562372", "short_name": "plasticovayazhizn"}, "id": "481507207301564224", "emoticons": ["😕"]}}, {"body": "🤖", "url": "mxc://matrix.agreiter.ch/mUKhEnVwXpuNaPzrdHLFYdTw", "info": {"w": 256, "h": 256, "size": 171185, "mimetype": "image/png", "thumbnail_url": "mxc://matrix.agreiter.ch/mUKhEnVwXpuNaPzrdHLFYdTw", "thumbnail_info": {"w": 256, "h": 256, "size": 171185, "mimetype": "image/png"}}, "id": "tg-481507207301564227", "net.maunium.telegram.sticker": {"pack": {"id": "481507207301562372", "short_name": "plasticovayazhizn"}, "id": "481507207301564227", "emoticons": ["🤖"]}}, {"body": "😬", "url": "mxc://matrix.agreiter.ch/SXcyyFjaTSNDSmhViqZsONHt", "info": {"w": 256, "h": 256, "size": 74920, "mimetype": "image/png", "thumbnail_url": "mxc://matrix.agreiter.ch/SXcyyFjaTSNDSmhViqZsONHt", "thumbnail_info": {"w": 256, "h": 256, "size": 74920, "mimetype": "image/png"}}, "id": "tg-481507207301564228", "net.maunium.telegram.sticker": {"pack": {"id": "481507207301562372", "short_name": "plasticovayazhizn"}, "id": "481507207301564228", "emoticons": ["😬"]}}, {"body": "📞", "url": "mxc://matrix.agreiter.ch/RGynzZFqRppGXzOpoSiazEnh", "info": {"w": 256, "h": 256, "size": 53426, "mimetype": "image/png", "thumbnail_url": "mxc://matrix.agreiter.ch/RGynzZFqRppGXzOpoSiazEnh", "thumbnail_info": {"w": 256, "h": 256, "size": 53426, "mimetype": "image/png"}}, "id": "tg-481507207301564286", "net.maunium.telegram.sticker": {"pack": {"id": "481507207301562372", "short_name": "plasticovayazhizn"}, "id": "481507207301564286", "emoticons": ["📞"]}}, {"body": "😂", "url": "mxc://matrix.agreiter.ch/feiiestFoZlHgTeErPPWkHaW", "info": {"w": 256, "h": 256, "size": 112377, "mimetype": "image/png", "thumbnail_url": "mxc://matrix.agreiter.ch/feiiestFoZlHgTeErPPWkHaW", "thumbnail_info": {"w": 256, "h": 256, "size": 112377, "mimetype": "image/png"}}, "id": "tg-481507207301564229", "net.maunium.telegram.sticker": {"pack": {"id": "481507207301562372", "short_name": "plasticovayazhizn"}, "id": "481507207301564229", "emoticons": ["😂"]}}, {"body": "❤", "url": "mxc://matrix.agreiter.ch/mCFDGMfINaMhewivtbRtCodC", "info": {"w": 256, "h": 256, "size": 204357, "mimetype": "image/png", "thumbnail_url": "mxc://matrix.agreiter.ch/mCFDGMfINaMhewivtbRtCodC", "thumbnail_info": {"w": 256, "h": 256, "size": 204357, "mimetype": "image/png"}}, "id": "tg-481507207301564232", "net.maunium.telegram.sticker": {"pack": {"id": "481507207301562372", "short_name": "plasticovayazhizn"}, "id": "481507207301564232", "emoticons": ["❤"]}}, {"body": "🙃", "url": "mxc://matrix.agreiter.ch/HtFupmOzsWbSHQNyYIvidqyE", "info": {"w": 256, "h": 256, "size": 115579, "mimetype": "image/png", "thumbnail_url": "mxc://matrix.agreiter.ch/HtFupmOzsWbSHQNyYIvidqyE", "thumbnail_info": {"w": 256, "h": 256, "size": 115579, "mimetype": "image/png"}}, "id": "tg-481507207301564259", "net.maunium.telegram.sticker": {"pack": {"id": "481507207301562372", "short_name": "plasticovayazhizn"}, "id": "481507207301564259", "emoticons": ["🙃"]}}, {"body": "😞", "url": "mxc://matrix.agreiter.ch/NhZVsqTjDTPOtwybgWheJwRH", "info": {"w": 256, "h": 256, "size": 196646, "mimetype": "image/png", "thumbnail_url": "mxc://matrix.agreiter.ch/NhZVsqTjDTPOtwybgWheJwRH", "thumbnail_info": {"w": 256, "h": 256, "size": 196646, "mimetype": "image/png"}}, "id": "tg-481507207301564260", "net.maunium.telegram.sticker": {"pack": {"id": "481507207301562372", "short_name": "plasticovayazhizn"}, "id": "481507207301564260", "emoticons": ["😞"]}}, {"body": "🙄", "url": "mxc://matrix.agreiter.ch/iIaDUXuQqWtzpcoKTjOXVfSX", "info": {"w": 256, "h": 256, "size": 194012, "mimetype": "image/png", "thumbnail_url": "mxc://matrix.agreiter.ch/iIaDUXuQqWtzpcoKTjOXVfSX", "thumbnail_info": {"w": 256, "h": 256, "size": 194012, "mimetype": "image/png"}}, "id": "tg-481507207301564262", "net.maunium.telegram.sticker": {"pack": {"id": "481507207301562372", "short_name": "plasticovayazhizn"}, "id": "481507207301564262", "emoticons": ["🙄"]}}, {"body": "😆", "url": "mxc://matrix.agreiter.ch/ZmaLFAFwlZxxJjhhAAFoIIAb", "info": {"w": 256, "h": 256, "size": 182688, "mimetype": "image/png", "thumbnail_url": "mxc://matrix.agreiter.ch/ZmaLFAFwlZxxJjhhAAFoIIAb", "thumbnail_info": {"w": 256, "h": 256, "size": 182688, "mimetype": "image/png"}}, "id": "tg-481507207301564269", "net.maunium.telegram.sticker": {"pack": {"id": "481507207301562372", "short_name": "plasticovayazhizn"}, "id": "481507207301564269", "emoticons": ["😆"]}}, {"body": "❤️", "url": "mxc://matrix.agreiter.ch/dUcLPtDPVbaPXMLpcnubddky", "info": {"w": 256, "h": 256, "size": 63481, "mimetype": "image/png", "thumbnail_url": "mxc://matrix.agreiter.ch/dUcLPtDPVbaPXMLpcnubddky", "thumbnail_info": {"w": 256, "h": 256, "size": 63481, "mimetype": "image/png"}}, "id": "tg-481507207301564273", "net.maunium.telegram.sticker": {"pack": {"id": "481507207301562372", "short_name": "plasticovayazhizn"}, "id": "481507207301564273", "emoticons": ["❤"]}}, {"body": "🍷", "url": "mxc://matrix.agreiter.ch/fyGOjncaMgGKHqmmTIkOMQgW", "info": {"w": 256, "h": 256, "size": 192358, "mimetype": "image/png", "thumbnail_url": "mxc://matrix.agreiter.ch/fyGOjncaMgGKHqmmTIkOMQgW", "thumbnail_info": {"w": 256, "h": 256, "size": 192358, "mimetype": "image/png"}}, "id": "tg-481507207301564275", "net.maunium.telegram.sticker": {"pack": {"id": "481507207301562372", "short_name": "plasticovayazhizn"}, "id": "481507207301564275", "emoticons": ["🍷"]}}, {"body": "🙄", "url": "mxc://matrix.agreiter.ch/EelASCMZURGSkIYFFIRZKjlx", "info": {"w": 256, "h": 256, "size": 128875, "mimetype": "image/png", "thumbnail_url": "mxc://matrix.agreiter.ch/EelASCMZURGSkIYFFIRZKjlx", "thumbnail_info": {"w": 256, "h": 256, "size": 128875, "mimetype": "image/png"}}, "id": "tg-481507207301564276", "net.maunium.telegram.sticker": {"pack": {"id": "481507207301562372", "short_name": "plasticovayazhizn"}, "id": "481507207301564276", "emoticons": ["🙄"]}}, {"body": "🐕", "url": "mxc://matrix.agreiter.ch/sOBWTnkowHIUgVmwRFuNEHDR", "info": {"w": 256, "h": 256, "size": 188149, "mimetype": "image/png", "thumbnail_url": "mxc://matrix.agreiter.ch/sOBWTnkowHIUgVmwRFuNEHDR", "thumbnail_info": {"w": 256, "h": 256, "size": 188149, "mimetype": "image/png"}}, "id": "tg-481507207301564277", "net.maunium.telegram.sticker": {"pack": {"id": "481507207301562372", "short_name": "plasticovayazhizn"}, "id": "481507207301564277", "emoticons": ["🐕"]}}, {"body": "😠", "url": "mxc://matrix.agreiter.ch/iJwLqQsgTmdnrdKEPBSkzTvF", "info": {"w": 256, "h": 256, "size": 82339, "mimetype": "image/png", "thumbnail_url": "mxc://matrix.agreiter.ch/iJwLqQsgTmdnrdKEPBSkzTvF", "thumbnail_info": {"w": 256, "h": 256, "size": 82339, "mimetype": "image/png"}}, "id": "tg-481507207301564278", "net.maunium.telegram.sticker": {"pack": {"id": "481507207301562372", "short_name": "plasticovayazhizn"}, "id": "481507207301564278", "emoticons": ["😠"]}}, {"body": "😱", "url": "mxc://matrix.agreiter.ch/gTpBNGxyZJdCvnYJIqqyXDbu", "info": {"w": 256, "h": 256, "size": 109298, "mimetype": "image/png", "thumbnail_url": "mxc://matrix.agreiter.ch/gTpBNGxyZJdCvnYJIqqyXDbu", "thumbnail_info": {"w": 256, "h": 256, "size": 109298, "mimetype": "image/png"}}, "id": "tg-481507207301564279", "net.maunium.telegram.sticker": {"pack": {"id": "481507207301562372", "short_name": "plasticovayazhizn"}, "id": "481507207301564279", "emoticons": ["😱"]}}, {"body": "❤️", "url": "mxc://matrix.agreiter.ch/dOusyunPuHYKYukTnQqBzRMk", "info": {"w": 256, "h": 256, "size": 44048, "mimetype": "image/png", "thumbnail_url": "mxc://matrix.agreiter.ch/dOusyunPuHYKYukTnQqBzRMk", "thumbnail_info": {"w": 256, "h": 256, "size": 44048, "mimetype": "image/png"}}, "id": "tg-481507207301564284", "net.maunium.telegram.sticker": {"pack": {"id": "481507207301562372", "short_name": "plasticovayazhizn"}, "id": "481507207301564284", "emoticons": ["❤"]}}, {"body": "🦊", "url": "mxc://matrix.agreiter.ch/eAwUEqzywFzRlqfsrrGWDAxQ", "info": {"w": 256, "h": 256, "size": 62544, "mimetype": "image/png", "thumbnail_url": "mxc://matrix.agreiter.ch/eAwUEqzywFzRlqfsrrGWDAxQ", "thumbnail_info": {"w": 256, "h": 256, "size": 62544, "mimetype": "image/png"}}, "id": "tg-481507207301564285", "net.maunium.telegram.sticker": {"pack": {"id": "481507207301562372", "short_name": "plasticovayazhizn"}, "id": "481507207301564285", "emoticons": ["🦊"]}}, {"body": "😕", "url": "mxc://matrix.agreiter.ch/QoxvihGIoGprPNflLPtpFTVW", "info": {"w": 256, "h": 256, "size": 79750, "mimetype": "image/png", "thumbnail_url": "mxc://matrix.agreiter.ch/QoxvihGIoGprPNflLPtpFTVW", "thumbnail_info": {"w": 256, "h": 256, "size": 79750, "mimetype": "image/png"}}, "id": "tg-481507207301564287", "net.maunium.telegram.sticker": {"pack": {"id": "481507207301562372", "short_name": "plasticovayazhizn"}, "id": "481507207301564287", "emoticons": ["😕"]}}, {"body": "👍", "url": "mxc://matrix.agreiter.ch/ILHfNosNSHiUfbutlbdOuVsM", "info": {"w": 256, "h": 256, "size": 69697, "mimetype": "image/png", "thumbnail_url": "mxc://matrix.agreiter.ch/ILHfNosNSHiUfbutlbdOuVsM", "thumbnail_info": {"w": 256, "h": 256, "size": 69697, "mimetype": "image/png"}}, "id": "tg-481507207301564289", "net.maunium.telegram.sticker": {"pack": {"id": "481507207301562372", "short_name": "plasticovayazhizn"}, "id": "481507207301564289", "emoticons": ["👍"]}}, {"body": "😥", "url": "mxc://matrix.agreiter.ch/KYgPTyyhLDlAVzkpsPbzXqBl", "info": {"w": 256, "h": 256, "size": 47363, "mimetype": "image/png", "thumbnail_url": "mxc://matrix.agreiter.ch/KYgPTyyhLDlAVzkpsPbzXqBl", "thumbnail_info": {"w": 256, "h": 256, "size": 47363, "mimetype": "image/png"}}, "id": "tg-481507207301564290", "net.maunium.telegram.sticker": {"pack": {"id": "481507207301562372", "short_name": "plasticovayazhizn"}, "id": "481507207301564290", "emoticons": ["😥"]}}, {"body": "😬", "url": "mxc://matrix.agreiter.ch/VYcrItHRYBLvBwQgujXqDsEk", "info": {"w": 256, "h": 256, "size": 95781, "mimetype": "image/png", "thumbnail_url": "mxc://matrix.agreiter.ch/VYcrItHRYBLvBwQgujXqDsEk", "thumbnail_info": {"w": 256, "h": 256, "size": 95781, "mimetype": "image/png"}}, "id": "tg-481507207301564291", "net.maunium.telegram.sticker": {"pack": {"id": "481507207301562372", "short_name": "plasticovayazhizn"}, "id": "481507207301564291", "emoticons": ["😬"]}}, {"body": "🤖", "url": "mxc://matrix.agreiter.ch/NZhvIpBjkQmAYizpKLYWUSyf", "info": {"w": 256, "h": 256, "size": 112512, "mimetype": "image/png", "thumbnail_url": "mxc://matrix.agreiter.ch/NZhvIpBjkQmAYizpKLYWUSyf", "thumbnail_info": {"w": 256, "h": 256, "size": 112512, "mimetype": "image/png"}}, "id": "tg-481507207301564292", "net.maunium.telegram.sticker": {"pack": {"id": "481507207301562372", "short_name": "plasticovayazhizn"}, "id": "481507207301564292", "emoticons": ["🤖"]}}, {"body": "🙂", "url": "mxc://matrix.agreiter.ch/GgpclaCVLAopxZHFBPAUlckE", "info": {"w": 256, "h": 256, "size": 103727, "mimetype": "image/png", "thumbnail_url": "mxc://matrix.agreiter.ch/GgpclaCVLAopxZHFBPAUlckE", "thumbnail_info": {"w": 256, "h": 256, "size": 103727, "mimetype": "image/png"}}, "id": "tg-481507207301564348", "net.maunium.telegram.sticker": {"pack": {"id": "481507207301562372", "short_name": "plasticovayazhizn"}, "id": "481507207301564348", "emoticons": ["🙂"]}}, {"body": "😎", "url": "mxc://matrix.agreiter.ch/wsVLrGpNXMvuOasZLFLiFaae", "info": {"w": 256, "h": 256, "size": 93744, "mimetype": "image/png", "thumbnail_url": "mxc://matrix.agreiter.ch/wsVLrGpNXMvuOasZLFLiFaae", "thumbnail_info": {"w": 256, "h": 256, "size": 93744, "mimetype": "image/png"}}, "id": "tg-481507207301564349", "net.maunium.telegram.sticker": {"pack": {"id": "481507207301562372", "short_name": "plasticovayazhizn"}, "id": "481507207301564349", "emoticons": ["😎"]}}]}